examples/__init__.py
examples/backward_modes.py
examples/bundle_adjustment.py
examples/homography_estimation.py
examples/motion_planning_2d.py
examples/se2_inverse.py
examples/se2_planning.py
examples/simple_example.py
examples/state_estimation_2d.py
examples/tactile_pose_estimation.py
tests/__init__.py
tests/decorators.py
tests/test_dlm_perturbation.py
tests/test_pgo_benchmark.py
tests/test_theseus_layer.py
tests/core/__init__.py
tests/core/common.py
tests/core/test_cost_function.py
tests/core/test_cost_weight.py
tests/core/test_manifold.py
tests/core/test_objective.py
tests/core/test_robust_cost.py
tests/core/test_theseus_function.py
tests/core/test_variable.py
tests/core/test_vectorizer.py
tests/extlib/__init__.py
tests/extlib/test_baspacho.py
tests/extlib/test_baspacho_simple.py
tests/extlib/test_cusolver_lu_solver.py
tests/extlib/test_mat_mult.py
tests/geometry/__init__.py
tests/geometry/common.py
tests/geometry/point_types_mypy_check.py
tests/geometry/test_point_types.py
tests/geometry/test_se2.py
tests/geometry/test_se3.py
tests/geometry/test_so2.py
tests/geometry/test_so3.py
tests/geometry/test_vector.py
theseus/__init__.py
theseus/constants.py
theseus/theseus_layer.py
theseus/core/__init__.py
theseus/core/cost_function.py
theseus/core/cost_weight.py
theseus/core/objective.py
theseus/core/robust_cost_function.py
theseus/core/robust_loss.py
theseus/core/theseus_function.py
theseus/core/variable.py
theseus/core/vectorizer.py
theseus/embodied/__init__.py
theseus/embodied/collision/__init__.py
theseus/embodied/collision/collision.py
theseus/embodied/collision/eff_obj_contact.py
theseus/embodied/collision/signed_distance_field.py
theseus/embodied/kinematics/__init__.py
theseus/embodied/kinematics/kinematics_model.py
theseus/embodied/measurements/__init__.py
theseus/embodied/measurements/between.py
theseus/embodied/measurements/moving_frame_between.py
theseus/embodied/measurements/reprojection.py
theseus/embodied/misc/__init__.py
theseus_ai_nightly-2023.4.21.dist-info/LICENSE
theseus_ai_nightly-2023.4.21.dist-info/METADATA
theseus_ai_nightly-2023.4.21.dist-info/WHEEL
theseus_ai_nightly-2023.4.21.dist-info/top_level.txt
theseus_ai_nightly-2023.4.21.dist-info/RECORD
