Metadata-Version: 2.1
Name: theseus-ai-nightly
Version: 2023.4.21
Summary: A library for differentiable nonlinear optimization.
Home-page: https://github.com/facebookresearch/theseus
Author: Meta Research
Keywords: differentiable optimization,nonlinear least squares,factor graphs
Classifier: Programming Language :: Python :: 3
Classifier: License :: OSI Approved :: MIT License
Classifier: Intended Audience :: Science/Research
Classifier: Topic :: Scientific/Engineering :: Artificial Intelligence
Requires-Python: >=3.8
License-File: LICENSE
Requires-Dist: numpy (>=1.19.2)
Requires-Dist: scipy (>=1.5.3)
Requires-Dist: scikit-sparse (>=0.4.5)
Requires-Dist: pytest (>=6.2.1)
Requires-Dist: pybind11 (>=2.7.1)
Requires-Dist: semantic-version (==2.10.0)
Provides-Extra: dev
Requires-Dist: numpy (>=1.19.2) ; extra == 'dev'
Requires-Dist: scipy (>=1.5.3) ; extra == 'dev'
Requires-Dist: scikit-sparse (>=0.4.5) ; extra == 'dev'
Requires-Dist: pytest (>=6.2.1) ; extra == 'dev'
Requires-Dist: pybind11 (>=2.7.1) ; extra == 'dev'
Requires-Dist: semantic-version (==2.10.0) ; extra == 'dev'
Requires-Dist: black (>=20.8b1) ; extra == 'dev'
Requires-Dist: flake8 (>=3.8.4) ; extra == 'dev'
Requires-Dist: mypy (>=0.981) ; extra == 'dev'
Requires-Dist: pre-commit (>=2.9.2) ; extra == 'dev'
Requires-Dist: isort (>=5.6.4) ; extra == 'dev'
Requires-Dist: differentiable-robot-model (>=0.2.3) ; extra == 'dev'
Requires-Dist: types-PyYAML (==5.4.3) ; extra == 'dev'
Requires-Dist: mock (>=4.0.3) ; extra == 'dev'
Requires-Dist: types-mock (>=4.0.8) ; extra == 'dev'
Requires-Dist: Sphinx (==5.0.2) ; extra == 'dev'
Requires-Dist: sphinx-rtd-theme (==1.0.0) ; extra == 'dev'
